adafruit_circuitpython_is31fl3741-1.5.6.dist-info/licenses/LICENSE
adafruit_is31fl3741/__init__.py
adafruit_is31fl3741/adafruit_ledglasses.py
adafruit_is31fl3741/adafruit_rgbmatrixqt.py
adafruit_is31fl3741/is31fl3741_pixelbuf.py
adafruit_is31fl3741/issi_evb.py
adafruit_is31fl3741/led_glasses_animation.py
adafruit_is31fl3741/led_glasses_map.py
adafruit_circuitpython_is31fl3741-1.5.6.dist-info/METADATA
adafruit_circuitpython_is31fl3741-1.5.6.dist-info/WHEEL
adafruit_circuitpython_is31fl3741-1.5.6.dist-info/top_level.txt
adafruit_circuitpython_is31fl3741-1.5.6.dist-info/RECORD
