Metadata-Version: 2.4
Name: adafruit-circuitpython-is31fl3741
Version: 1.5.6
Summary: CircuitPython library for IS31FL3741 RGB LED matrices.
Author-email: Adafruit Industries <circuitpython@adafruit.com>
License: MIT
Project-URL: Homepage, https://github.com/adafruit/Adafruit_CircuitPython_IS31FL3741
Keywords: adafruit,is31fl3741,led,matrix,charlieplex,featherwingbreakout,hardware,micropython,circuitpython
Classifier: Intended Audience :: Developers
Classifier: Topic :: Software Development :: Libraries
Classifier: Topic :: Software Development :: Embedded Systems
Classifier: Topic :: System :: Hardware
Classifier: License :: OSI Approved :: MIT License
Classifier: Programming Language :: Python :: 3
License-File: LICENSE
Requires-Dist: Adafruit-Blinka
Requires-Dist: adafruit-circuitpython-framebuf
Requires-Dist: adafruit-circuitpython-busdevice
Requires-Dist: adafruit-circuitpython-typing~=1.6
Requires-Dist: adafruit-circuitpython-register
Provides-Extra: optional
Requires-Dist: pillow; extra == "optional"
Dynamic: license-file
